<?xml version="1.0"?>

<entity-mappings xmlns="http://java.sun.com/xml/ns/persistence/orm" xmlns:xsi="http://www.w3.org/2001/XMLSchema-instance" version="1.0" xsi:schemaLocation="http://java.sun.com/xml/ns/persistence/orm http://java.sun.com/xml/ns/persistence/orm_1_0.xsd">
	<persistence-unit-metadata>
		<xml-mapping-metadata-complete/>
		<persistence-unit-defaults>
			<access>PROPERTY</access>
		</persistence-unit-defaults>
	</persistence-unit-metadata>
	<mapped-superclass class="com.yyms.adp.aaa.model.impl.YCustomerModelImpl">
		<attributes>
			<id name="yCustomerId" />
			<basic name="uuid">
				<column name="UUID_" />
			</basic>
			<basic name="groupId" />
			<basic name="companyId" />
			<basic name="userId" />
			<basic name="userName" />
			<basic name="createDate">
				<temporal>TIMESTAMP</temporal>
			</basic>
			<basic name="modifiedDate">
				<temporal>TIMESTAMP</temporal>
			</basic>
			<basic name="customerName" />
			<basic name="customerEmail" />
			<basic name="customerAddress" />
			<basic name="customerNRC" />
			<basic name="customerContact" />
			<basic name="payment" />
			<basic name="yServicesId" />
			<transient name="YCustomerId" />
			<transient name="YServicesId" />
			<transient name="modelAttributes" />
			<transient name="primaryKey" />
			<transient name="primaryKeyObj" />
			<transient name="userUuid" />
		</attributes>
	</mapped-superclass>
	<mapped-superclass class="com.yyms.adp.aaa.model.impl.YServicesModelImpl">
		<attributes>
			<id name="yServicesId" />
			<basic name="uuid">
				<column name="UUID_" />
			</basic>
			<basic name="groupId" />
			<basic name="companyId" />
			<basic name="userId" />
			<basic name="userName" />
			<basic name="createDate">
				<temporal>TIMESTAMP</temporal>
			</basic>
			<basic name="modifiedDate">
				<temporal>TIMESTAMP</temporal>
			</basic>
			<basic name="servicesName" />
			<basic name="servicesPrice" />
			<basic name="servicesDes" />
			<transient name="YServicesId" />
			<transient name="modelAttributes" />
			<transient name="primaryKey" />
			<transient name="primaryKeyObj" />
			<transient name="userUuid" />
		</attributes>
	</mapped-superclass>
	<entity class="com.yyms.adp.aaa.model.impl.YCustomerImpl" name="YCustomer">
		<table name="CS_YCustomer" />
		<attributes />
	</entity>
	<entity class="com.yyms.adp.aaa.model.impl.YServicesImpl" name="YServices">
		<table name="CS_YServices" />
		<attributes />
	</entity>
</entity-mappings>